neovim_sh/__init__.py
neovim_sh/__main__.py
neovim_sh-0.1.1.dist-info/METADATA
neovim_sh-0.1.1.dist-info/WHEEL
neovim_sh-0.1.1.dist-info/entry_points.txt
neovim_sh-0.1.1.dist-info/top_level.txt
neovim_sh-0.1.1.dist-info/RECORD
