Metadata-Version: 2.1
Name: neovim-sh
Version: 0.1.1
Summary: Neovim wrapper project to install as a script
Home-page: https://github.com/miki725/neovim-sh
License: MIT
Keywords: neovim
Platform: UNKNOWN
Classifier: Intended Audience :: Developers
Classifier: Natural Language :: English
Classifier: License :: OSI Approved :: MIT License
Requires-Dist: neovim
